_build_tidalpy.py
Benchmarks & Performance/Performance/performance suite/multilayer_radial_solver.py
Benchmarks & Performance/Performance/performance suite/multimode_solver.py
Benchmarks & Performance/Performance/performance suite/performance_base.py
Benchmarks & Performance/Performance/performance suite/performance_build_world.py
Benchmarks & Performance/Performance/performance suite/performance_complex_compliance_func.py
Benchmarks & Performance/Performance/performance suite/performance_eccentricity_func.py
Benchmarks & Performance/Performance/performance suite/performance_quick_calcs.py
Benchmarks & Performance/Performance/performance suite/performance_tides.py
Benchmarks & Performance/Performance/performance suite/run_suite.py
Tests/Test_Functions/test_rheology.py
Tests/Test_Math/test_utilities_complex.py
Tests/Test_Math/test_utilities_numerics.py
Tests/Test_Math/test_utilities_special.py
Tests/Test_Old/Test_SetA_Package/test_a_version.py
Tests/Test_Old/Test_SetA_Package/test_io.py
Tests/Test_Old/Test_SetA_Package/test_tidalpy_config.py
Tests/Test_Old/Test_SetB_Package/test_b_utilities_functools.py
Tests/Test_Old/Test_SetB_Package/test_b_utilities_numpy.py
Tests/Test_Old/Test_SetB_Package/test_c_tools_conversions.py
Tests/Test_Old/Test_SetB_Package/test_c_tools_timing.py
Tests/Test_Old/Test_SetB_Package/test_d_basic_classes.py
Tests/Test_Old/Test_SetB_Package/test_g_math_special_funcs.py
Tests/Test_Old/Test_SetB_Package/test_h_voxel_volume.py
Tests/Test_Old/Test_SetB_Package/test_i_spherical_mass.py
Tests/Test_Old/Test_SetE_Functional/test_a_performance_funcs.py
Tests/Test_Old/Test_SetF_Functional/Test_Dynamics/test_dual_dissipation.py
Tests/Test_Old/Test_SetF_Functional/Test_Dynamics/test_single_dissipation.py
Tests/Test_Old/Test_SetF_Functional/Test_Rheology/test_compliance_funcs.py
Tests/Test_Old/Test_SetF_Functional/Test_Rheology/test_partialmelt_funcs.py
Tests/Test_Old/Test_SetF_Functional/Test_Tides/test_a_orbital_funcs.py
tidalpy-0.6.11.dist-info/licenses/LICENSE.md
tidalpy-0.6.11.dist-info/METADATA
tidalpy-0.6.11.dist-info/WHEEL
tidalpy-0.6.11.dist-info/entry_points.txt
tidalpy-0.6.11.dist-info/top_level.txt
tidalpy-0.6.11.dist-info/RECORD
