Metadata-Version: 2.4
Name: TidalPy
Version: 0.6.11
Summary: Tidal Dynamics and Thermal-Orbital Evolution Software Suite Implemented in Cython and Python
Author-email: "Joe P. Renaud" <TidalPy@gmail.com>
License-Expression: CC-BY-NC-SA-4.0
Project-URL: Homepage, https://github.com/jrenaud90/TidalPy
Project-URL: Bug Tracker, https://github.com/jrenaud90/TidalPy/issues
Keywords: Scientific Computing,Scientific Modeling,Astrophysics,Astronomy,Planets,Moons,Exoplanets,Planetary Science,Planetary Interiors,Orbital Dynamics,Tides,Tidal Dynamics,Tidal Heating,Numerical Integration
Classifier: Development Status :: 3 - Alpha
Classifier: Operating System :: Microsoft :: Windows
Classifier: Operating System :: MacOS
Classifier: Operating System :: POSIX :: Linux
Classifier: Programming Language :: Cython
Classifier: Programming Language :: Python :: 3.10
Classifier: Programming Language :: Python :: 3.11
Classifier: Programming Language :: Python :: 3.12
Classifier: Programming Language :: Python :: 3.13
Classifier: Programming Language :: Python :: Implementation :: CPython
Classifier: Natural Language :: English
Classifier: Intended Audience :: Science/Research
Classifier: Intended Audience :: Developers
Classifier: Intended Audience :: Education
Classifier: Topic :: Scientific/Engineering
Classifier: Topic :: Scientific/Engineering :: Mathematics
Classifier: Topic :: Scientific/Engineering :: Astronomy
Classifier: Topic :: Scientific/Engineering :: Physics
Classifier: Natural Language :: English
Requires-Python: <3.14,>=3.9
License-File: LICENSE.md
Requires-Dist: numba>=0.54.1
Requires-Dist: numpy<2.3,>=1.22
Requires-Dist: scipy>=1.9.3
Requires-Dist: platformdirs>=3.11.0
Requires-Dist: toml>=0.10.2
Requires-Dist: dill>=0.3.2
Requires-Dist: psutil>=5.8.0
Requires-Dist: pathos>=0.2.0
Requires-Dist: cyrk<0.16.0,>=0.15.1
Requires-Dist: astropy
Requires-Dist: astroquery
Requires-Dist: ipympl<0.10.0,>=0.9.6
Requires-Dist: matplotlib<5.0.0,>=3.4.2
Requires-Dist: cmcrameri
Provides-Extra: dev
Requires-Dist: jupyter; extra == "dev"
Requires-Dist: pytest; extra == "dev"
Requires-Dist: cmcrameri<2.0,>=1.4; extra == "dev"
Requires-Dist: matplotlib>=3.4.2; extra == "dev"
Requires-Dist: palettable>=3.3.0; extra == "dev"
Requires-Dist: ipympl>=0.8.7; extra == "dev"
Requires-Dist: julia>=0.5.7; extra == "dev"
Requires-Dist: diffeqpy>=1.2.0; extra == "dev"
Provides-Extra: graphics
Requires-Dist: jupyter; extra == "graphics"
Requires-Dist: cmcrameri<2.0,>=1.4; extra == "graphics"
Requires-Dist: matplotlib>=3.4.2; extra == "graphics"
Requires-Dist: palettable>=3.3.0; extra == "graphics"
Requires-Dist: ipympl>=0.8.7; extra == "graphics"
Provides-Extra: burnman
Requires-Dist: autograd; extra == "burnman"
Requires-Dist: burnman<3,>=2.1.0; extra == "burnman"
Provides-Extra: cartopy
Requires-Dist: cartopy>=0.22.0; extra == "cartopy"
Provides-Extra: julia
Requires-Dist: julia>=0.5.7; extra == "julia"
Requires-Dist: diffeqpy>=1.2.0; extra == "julia"
Dynamic: license-file
